pelican_stat/__init__.py
pelican_stat/__main__.py
pelican_stat/collector.py
pelican_stat/plotter.py
pelican_stat-0.3.0.dist-info/entry_points.txt
pelican_stat-0.3.0.dist-info/LICENSE
pelican_stat-0.3.0.dist-info/WHEEL
pelican_stat-0.3.0.dist-info/METADATA
pelican_stat-0.3.0.dist-info/RECORD
