Metadata-Version: 2.1
Name: pelican-stat
Version: 0.3.0
Summary: Command line tool that generates pelican article statistics
License: MIT
Author: Wei Lee
Author-email: weilee.rx@gmail.com
Requires-Python: >=3.7.1,<4.0.0
Classifier: License :: OSI Approved :: MIT License
Classifier: Programming Language :: Python :: 3
Classifier: Programming Language :: Python :: 3.8
Classifier: Programming Language :: Python :: 3.9
Requires-Dist: Markdown (>=3.3.3,<4.0.0)
Requires-Dist: click (>=7.1.2,<8.0.0)
Requires-Dist: pandas (>=1.2.1,<2.0.0)
Requires-Dist: pelican (==4.5.4)
Requires-Dist: plotly (>=4.14.3,<5.0.0)
